[
    {"name": "Test Engineer"},
    {"name": "Web Developer"},
    {"name": "Receptionist"},
    {"name": "Instructional Designer"},
    {"name": "Clerk"},
    {"name": "District Manager"},
    {"name": "Devops Engineer"},
    {"name": "Procurement Agent"},
    {"name": "Visual Merchandiser"},
    {"name": "Repair Technician"},
    {"name": "Nurse Practitioner"},
    {"name": "Camp Counselor"},
    {"name": "Java Developer"},
    {"name": "Human Capital Consultant"},
    {"name": "Registered Nurse"},
    {"name": "HR Manager"},
    {"name": "Delivery Manager"},
    {"name": "Buyer"},
    {"name": "Account Executive"},
    {"name": "Professor of Mathematics"},
    {"name": "Internal Auditor"},
    {"name": "BI Manager"},
    {"name": "Water Resources Engineer"},
    {"name": "QA Tester"},
    {"name": "Grocery Clerk"},
    {"name": "Embedded Software Engineer"},
    {"name": "Auditor"},
    {"name": "Technology Specialist"},
    {"name": "Music Artist"},
    {"name": "Electrician"},
    {"name": "Financial Planner"},
    {"name": "Database Developer"},
    {"name": "Service Desk Analyst"},
    {"name": "Systems Architect"},
    {"name": "Civil Engineer"},
    {"name": "Property Manager"},
    {"name": "Salesforce Developer"},
    {"name": "Business Developer"},
    {"name": "Auto Technician"},
    {"name": "Site Reliability Engineer"},
    {"name": "Electrical Designer"},
    {"name": "Managing Partner"},
    {"name": "CAD Engineer"},
    {"name": "Forensic Scientist"},
    {"name": "Registrar"},
    {"name": "Research Scientist"},
    {"name": "IT Analyst"},
    {"name": "Consultant"},
    {"name": "CRO"},
    {"name": "Market Analyst"},
    {"name": "Librarian"},
    {"name": "Contract Administrator"},
    {"name": "BI Analyst"},
    {"name": "Compliance Analyst"},
    {"name": "Claims Examiner"},
    {"name": "Supply Chain Manager"},
    {"name": "Customer Service Manager"},
    {"name": "HR Business Partner"},
    {"name": "Material Handler"},
    {"name": "Systems Administrator"},
    {"name": "Business Operations Manager"},
    {"name": "Call Center Representative"},
    {"name": "Sourcer"},
    {"name": "Technical Project Manager"},
    {"name": "Artist"},
    {"name": "Trader"},
    {"name": "Reporting Analyst"},
    {"name": "Underwriter"},
    {"name": "Service Manager"},
    {"name": "Cashier and Checker"},
    {"name": "Event Coordinator"},
    {"name": "Researcher"},
    {"name": "Marketing Coordinator"},
    {"name": "Implementation Manager"},
    {"name": "Technical Support Engineer"},
    {"name": "Full Stack Engineer"},
    {"name": "Systems Engineer"},
    {"name": "Food Scientist"},
    {"name": "Office Manager"},
    {"name": "Photographer"},
    {"name": "Real Estate Manager"},
    {"name": "Product Manager"},
    {"name": "Automation Engineer"},
    {"name": "Optical Engineer"},
    {"name": "Concept Artist"},
    {"name": "Product Marketing"},
    {"name": "Storage Administrator"},
    {"name": "Social Worker"},
    {"name": "Bartender"},
    {"name": "Writer"},
    {"name": "HR Associate"},
    {"name": "IT Manager"},
    {"name": "Program Coordinator"},
    {"name": "Research Fellow"},
    {"name": "Pilot"},
    {"name": "Territory Manager"},
    {"name": "Robotics Engineer"},
    {"name": "Legal Advisor"},
    {"name": "Sales Associate"},
    {"name": "Order Selector"},
    {"name": "Data Analyst"},
    {"name": "Attorney"},
    {"name": "Pharmacy Technician"},
    {"name": "Quantitative Researcher"},
    {"name": "Investment Banking Analyst"},
    {"name": "Data Center Technician"},
    {"name": "Media Specialist"},
    {"name": "Team Member"},
    {"name": "Accounting Manager"},
    {"name": "General Manager"},
    {"name": "Professor"},
    {"name": "Director"},
    {"name": "Content Manager"},
    {"name": "Journalist"},
    {"name": "Exercise Physiologist"},
    {"name": "Operations Manager"},
    {"name": "Engineer"},
    {"name": "Computational Biologist"},
    {"name": "Transportation Analyst"},
    {"name": "Behavior Therapist"},
    {"name": "Corporate Recruiter"},
    {"name": "Medical Coder"},
    {"name": "Sourcing Specialist"},
    {"name": "Inbound Sales Representative"},
    {"name": "Production Planner"},
    {"name": "Implementation Consultant"},
    {"name": "Digital Marketing"},
    {"name": "Outside Sales"},
    {"name": "Parts Sales Manager"},
    {"name": "Computer Technician"},
    {"name": "Insurance Agent"},
    {"name": "Brand Manager"},
    {"name": "Transportation Manager"},
    {"name": "Sales Representative"},
    {"name": "Research Analyst"},
    {"name": "Area Manager"},
    {"name": "Technical Program Manager"},
    {"name": "Technical Manager"},
    {"name": "Painter"},
    {"name": "Database Administrator"},
    {"name": "Data Manager"},
    {"name": "Guest Services"},
    {"name": "Finance Manager"},
    {"name": "Machine Operator"},
    {"name": "Editorial Assistant"},
    {"name": "Operator"},
    {"name": "Network Engineer"},
    {"name": "Clinical Nurse"},
    {"name": "Food Technologist"},
    {"name": "Support Specialist"},
    {"name": "Floral Designer"},
    {"name": "Programmer Analyst"},
    {"name": "Operations Analyst"},
    {"name": "Barista"},
    {"name": "Manufacturing Engineer"},
    {"name": "Marketing"},
    {"name": "Physics Teacher"},
    {"name": "Interpreter"},
    {"name": "Licensed Practical Nurse"},
    {"name": "IT Consultant"},
    {"name": "Merchandising Manager"},
    {"name": "Project Engineer"},
    {"name": "QA Manager"},
    {"name": "Language Analyst"},
    {"name": "Police Officer"},
    {"name": "CIO"},
    {"name": "Accounts Receivable"},
    {"name": "Field Service Engineer"},
    {"name": "Animator"},
    {"name": "UX Researcher"},
    {"name": "Functional Consultant"},
    {"name": "3D Artist"},
    {"name": "Technical Analyst"},
    {"name": "QA Analyst"},
    {"name": "Recruiting Coordinator"},
    {"name": "PR"},
    {"name": "Physician Assistant"},
    {"name": "Editor"},
    {"name": "Medical Assistant"},
    {"name": "Industrial Engineer"},
    {"name": "Back End Engineer"},
    {"name": "Designer"},
    {"name": "Teller"},
    {"name": "Logistics Analyst"},
    {"name": "Community Manager"},
    {"name": "Construction Estimator"},
    {"name": "Benefits Coordinator"},
    {"name": "Accounts Payable"},
    {"name": "Mobile Engineer"},
    {"name": "Nuclear Engineer"},
    {"name": "IT Specialist"},
    {"name": "Warehouse Worker"},
    {"name": "Language Teacher"},
    {"name": "Driver"},
    {"name": "Customer Relations"},
    {"name": "Systems Manager"},
    {"name": "Plant Manager"},
    {"name": "Risk Analyst"},
    {"name": "Technician"},
    {"name": "Implementation Specialist"},
    {"name": "Communications Coordinator"},
    {"name": "Real Estate Broker"},
    {"name": "Machine Learning Engineer"},
    {"name": "Territory Sales Manager"},
    {"name": "Database Engineer"},
    {"name": "QA Engineer"},
    {"name": "Technology Manager"},
    {"name": "Social Media Manager"},
    {"name": "Stock Clerk"},
    {"name": "Telecommunications Technician"},
    {"name": "Contract Specialist"},
    {"name": "Software Developer"},
    {"name": "Investigator"},
    {"name": "Bookkeeper"},
    {"name": "Maintenance Technician"},
    {"name": "Intelligence Analyst"},
    {"name": "IT Auditor"},
    {"name": "Service Representative"},
    {"name": "Drafter"},
    {"name": "Medical Scribe"},
    {"name": "Graphic Designer"},
    {"name": "Production Assistant"},
    {"name": "Executive Assistant"},
    {"name": "Event Planner"},
    {"name": "Payroll Specialist"},
    {"name": "Process Operator"},
    {"name": "Production Worker"},
    {"name": "Infrastructure Engineer"},
    {"name": "Quality Engineer"},
    {"name": "Hardware Engineer"},
    {"name": "Quality Manager"},
    {"name": "Copywriter"},
    {"name": "Electronics Engineer"},
    {"name": "Biostatistician"},
    {"name": "IT Administrator"},
    {"name": "Data Specialist"},
    {"name": "Firmware Engineer"},
    {"name": "Research Assistant"},
    {"name": "PR Manager"},
    {"name": "Physical Design Engineer"},
    {"name": "Chemical Engineer"},
    {"name": "Administrative Assistant"},
    {"name": "Actuary"},
    {"name": "Biologist"},
    {"name": "Enterprise Developer"},
    {"name": "Manager"},
    {"name": "Content Writer"},
    {"name": "Design Manager"},
    {"name": "Motion Graphics Designer"},
    {"name": "Product Engineer"},
    {"name": "Process Engineer"},
    {"name": "Field Technician"},
    {"name": "Paralegal"},
    {"name": "Web Designer"},
    {"name": "Verification Engineer"},
    {"name": "Laborer"},
    {"name": "Financial Reporting Manager"},
    {"name": "Support Technician"},
    {"name": "Special Education Teacher"},
    {"name": "Compliance Officer"},
    {"name": "Loan Processor"},
    {"name": "HR Specialist"},
    {"name": "Enterprise Architect"},
    {"name": "Electronics Technician"},
    {"name": "Geologist"},
    {"name": "Instructor"},
    {"name": "Information Security Analyst"},
    {"name": "Industrial Designer"},
    {"name": "Sales Engineer"},
    {"name": "Support Engineer"},
    {"name": "Game Developer"},
    {"name": "Education"},
    {"name": "Risk Manager"},
    {"name": "Clinical Data Manager"},
    {"name": "Billing Specialist"},
    {"name": "Forklift Operator"},
    {"name": "Physician Advisor"},
    {"name": "Office Administrator"},
    {"name": "Scrum Master"},
    {"name": "Delivery Driver"},
    {"name": "Medical Transcriptionist"},
    {"name": "Fraud Analyst"},
    {"name": "Channel Manager"},
    {"name": "Storage Engineer"},
    {"name": "Lab Assistant"},
    {"name": "Security"},
    {"name": "Practice Manager"},
    {"name": "SEO Analyst"},
    {"name": "Of Counsel"},
    {"name": "Claims Adjuster"},
    {"name": "Economist"},
    {"name": "IT Support Analyst"},
    {"name": "Technical Support"},
    {"name": "Accountant"},
    {"name": "Security Manager"},
    {"name": "Business Analyst"},
    {"name": "Counselor"},
    {"name": "Sales Development Representative"},
    {"name": "Help Desk Technician"},
    {"name": "CMO"},
    {"name": "Software Engineer"},
    {"name": "Process Technician"},
    {"name": "Bioinformatics Scientist"},
    {"name": "Commodity Manager"},
    {"name": "Analyst"},
    {"name": "Creative Manager"},
    {"name": "Real Estate Assistant"},
    {"name": "Healthcare Consultant"},
    {"name": "Athletic Trainer"},
    {"name": "Fashion Designer"},
    {"name": "Audio Engineer"},
    {"name": "HR Generalist"},
    {"name": "Sales Operations Manager"},
    {"name": "Cloud Engineer"},
    {"name": "Realtor"},
    {"name": "Social Studies Teacher"},
    {"name": "Advertising Manager"},
    {"name": "Physical Therapist"},
    {"name": "Design Engineer"},
    {"name": "Linux Engineer"},
    {"name": "Enterprise Account Manager"},
    {"name": "Business Development Associate"},
    {"name": "Production Manager"},
    {"name": "IT Technician"},
    {"name": "Community Relations Manager"},
    {"name": "Test Technician"},
    {"name": "File Clerk"},
    {"name": "Retail Sales Associate"},
    {"name": "Account Manager"},
    {"name": "QC Analyst"},
    {"name": "Inside Sales Representative"},
    {"name": "CAD Designer"},
    {"name": "HR Assistant"},
    {"name": "Psychiatric Technician"},
    {"name": "Animal Care Technician"},
    {"name": "Clinical Pharmacist"},
    {"name": "Oracle Consultant"},
    {"name": "Software Sales Representative"},
    {"name": "BI Engineer"},
    {"name": "Channel Sales Manager"},
    {"name": "Epidemiologist"},
    {"name": "Channel Account Manager"},
    {"name": "Leadership Development"},
    {"name": "Validation Engineer"},
    {"name": "Information Security Engineer"},
    {"name": "HR Consultant"},
    {"name": "Benefits Specialist"},
    {"name": "Inspector"},
    {"name": "Art Manager"},
    {"name": "Professor of History"},
    {"name": "Front End Engineer"},
    {"name": "Technical Account Manager"},
    {"name": "Medical Writer"},
    {"name": "Strategic Account Manager"},
    {"name": "SQL Developer"},
    {"name": "Strategy Manager"},
    {"name": "Payroll Manager"},
    {"name": "Project Manager"},
    {"name": "Release Manager"},
    {"name": "Materials Engineer"},
    {"name": "Truck Driver"},
    {"name": "Client Services Representative"},
    {"name": "Project Coordinator"},
    {"name": "Project Designer"},
    {"name": "Research Engineer"},
    {"name": "English Teacher"},
    {"name": "Program Manager"},
    {"name": "Chemist"},
    {"name": "Product Designer"},
    {"name": "Front Desk Agent"},
    {"name": "Demand Planner"},
    {"name": "Merchandiser"},
    {"name": "Store Manager"},
    {"name": "Solutions Engineer"},
    {"name": "Data Engineer"},
    {"name": "Technical Sourcer"},
    {"name": "Mechanical Engineer"},
    {"name": "Manufacturing Manager"},
    {"name": "Film Crew Member"},
    {"name": "Landman"},
    {"name": "Technical Writer"},
    {"name": "SAP Consultant"},
    {"name": "Power Systems Engineer"},
    {"name": "Security Officer"},
    {"name": "Procurement Analyst"},
    {"name": "Blockchain Developer"},
    {"name": "Regional Sales Manager"},
    {"name": "Controller"},
    {"name": "Public Health Advisor"},
    {"name": "Relationship Manager"},
    {"name": "Lab Technician"},
    {"name": "Purchasing Agent"},
    {"name": "Inventory Control Specialist"},
    {"name": "Software Development Engineer in Test"},
    {"name": "Data Scientist"},
    {"name": "Translator"},
    {"name": "Sales Manager"},
    {"name": "Environmental Specialist"},
    {"name": "Customer Success Manager"},
    {"name": "Financial Analyst"},
    {"name": "Product Owner"},
    {"name": "Technical Recruiter"},
    {"name": "Firefighter"},
    {"name": "Trainer"},
    {"name": "Housekeeper"},
    {"name": "UX Designer"},
    {"name": "Network Administrator"},
    {"name": "Technical Designer"},
    {"name": "Butcher"},
    {"name": "Recruiter"},
    {"name": "Business Development Manager"},
    {"name": "Supply Chain Analyst"},
    {"name": "Facilities Manager"},
    {"name": "Video Editor"},
    {"name": "RF Engineer"},
    {"name": "Data Entry"},
    {"name": "Instrument Technician"},
    {"name": "Safety Manager"},
    {"name": "Training Specialist"},
    {"name": "Information Security Specialist"},
    {"name": "Logistics Associate"},
    {"name": "IT Recruiter"},
    {"name": "Logistics Manager"},
    {"name": "Mechanic"},
    {"name": "Applications Engineer"},
    {"name": "Electrical Engineer"},
    {"name": "Analog Design Engineer"},
    {"name": "Communications Associate"},
    {"name": "Teacher"},
    {"name": "Janitor"},
    {"name": "Policy Analyst"},
    {"name": "Credit Manager"},
    {"name": "Development Specialist"}
]